exciting_environments/__init__.py
exciting_environments/core_env.py
exciting_environments/gym_wrapper.py
exciting_environments/registration.py
exciting_environments/spaces.py
exciting_environments/utils.py
exciting_environments/cart_pole/__init__.py
exciting_environments/cart_pole/cart_pole_env.py
exciting_environments/fluid_tank/__init__.py
exciting_environments/fluid_tank/fluid_tank_env.py
exciting_environments/mass_spring_damper/__init__.py
exciting_environments/mass_spring_damper/mass_spring_damper_env.py
exciting_environments/pendulum/__init__.py
exciting_environments/pendulum/pendulum_env.py
exciting_environments/pmsm/LUT_BRUSA_jax_grad.mat
exciting_environments/pmsm/LUT_SEW_jax_grad.mat
exciting_environments/pmsm/__init__.py
exciting_environments/pmsm/motor_parameters.py
exciting_environments/pmsm/pmsm_env.py
exciting_environments-0.2.4.dist-info/licenses/LICENSE
exciting_environments-0.2.4.dist-info/METADATA
exciting_environments-0.2.4.dist-info/WHEEL
exciting_environments-0.2.4.dist-info/top_level.txt
exciting_environments-0.2.4.dist-info/RECORD
