Metadata-Version: 2.4
Name: exciting_environments
Version: 0.2.4
Summary: Physical differential equations wrapped into Gymnasium environments
Author-email: Oliver Schweins <oliverjs@mail.uni-paderborn.de>, Hendrik Vater <vater@lea.uni-paderborn.de>
Project-URL: Homepage, https://excitingsystems.github.io/exciting-environments/
Classifier: Programming Language :: Python :: 3
Classifier: License :: OSI Approved :: MIT License
Classifier: Operating System :: OS Independent
Requires-Python: >=3.11
License-File: LICENSE
Requires-Dist: matplotlib==3.9.0
Requires-Dist: jax==0.4.28
Requires-Dist: jaxlib==0.4.28
Requires-Dist: chex==0.1.86
Requires-Dist: numpy==1.26.4
Requires-Dist: scipy==1.13.1
Requires-Dist: pytest==8.2.1
Requires-Dist: pytest-cov==5.0.0
Requires-Dist: diffrax==0.5.1
Requires-Dist: jax-dataclasses==1.6.0
Dynamic: license-file
